[1,["137e2fd81@6c48a"],["_textureSource"],["cc.SpriteFrame"],0,[[[{"name":"100102","rect":{"x":98,"y":630,"width":84,"height":302},"offset":{"x":1,"y":0},"originalSize":{"width":94,"height":302},"rotated":false,"capInsets":[0,0,0,0],"packable":true,"pixelsToUnit":100,"pivot":{"x":0.5,"y":0.5},"meshType":0}],[0],0,[0],[0],[0]],[[{"name":"100101","rect":{"x":3,"y":938,"width":83,"height":302},"offset":{"x":0.5,"y":0},"originalSize":{"width":94,"height":302},"rotated":true,"capInsets":[0,0,0,0],"packable":true,"pixelsToUnit":100,"pivot":{"x":0.5,"y":0.5},"meshType":0}],[0],0,[0],[0],[0]],[[{"name":"110302","rect":{"x":103,"y":3,"width":89,"height":302},"offset":{"x":0.5,"y":0},"originalSize":{"width":94,"height":302},"rotated":false,"capInsets":[0,0,0,0],"packable":true,"pixelsToUnit":100,"pivot":{"x":0.5,"y":0.5},"meshType":0}],[0],0,[0],[0],[0]],[[{"name":"100801","rect":{"x":702,"y":3,"width":289,"height":198},"offset":{"x":-0.5,"y":0},"originalSize":{"width":302,"height":198},"rotated":true,"capInsets":[0,0,0,0],"packable":true,"pixelsToUnit":100,"pivot":{"x":0.5,"y":0.5},"meshType":0}],[0],0,[0],[0],[0]],[[{"name":"100601","rect":{"x":288,"y":614,"width":94,"height":295},"offset":{"x":0,"y":1.5},"originalSize":{"width":94,"height":302},"rotated":false,"capInsets":[0,0,0,0],"packable":true,"pixelsToUnit":100,"pivot":{"x":0.5,"y":0.5},"meshType":0}],[0],0,[0],[0],[0]],[[{"name":"100402","rect":{"x":976,"y":698,"width":198,"height":43},"offset":{"x":0,"y":-0.5},"originalSize":{"width":198,"height":94},"rotated":true,"capInsets":[0,0,0,0],"packable":true,"pixelsToUnit":100,"pivot":{"x":0.5,"y":0.5},"meshType":0}],[0],0,[0],[0],[0]],[[{"name":"100803","rect":{"x":498,"y":3,"width":290,"height":198},"offset":{"x":0,"y":0},"originalSize":{"width":302,"height":198},"rotated":true,"capInsets":[0,0,0,0],"packable":true,"pixelsToUnit":100,"pivot":{"x":0.5,"y":0.5},"meshType":0}],[0],0,[0],[0],[0]],[[{"name":"110104","rect":{"x":706,"y":298,"width":94,"height":193},"offset":{"x":0,"y":0.5},"originalSize":{"width":94,"height":198},"rotated":true,"capInsets":[0,0,0,0],"packable":true,"pixelsToUnit":100,"pivot":{"x":0.5,"y":0.5},"meshType":0}],[0],0,[0],[0],[0]],[[{"name":"140104","rect":{"x":896,"y":698,"width":74,"height":94},"offset":{"x":0.5,"y":0},"originalSize":{"width":95,"height":94},"rotated":false,"capInsets":[0,0,0,0],"packable":true,"pixelsToUnit":100,"pivot":{"x":0.5,"y":0.5},"meshType":0}],[0],0,[0],[0],[0]],[[{"name":"100605","rect":{"x":311,"y":915,"width":100,"height":280},"offset":{"x":0,"y":-6},"originalSize":{"width":100,"height":320},"rotated":true,"capInsets":[0,0,0,0],"packable":true,"pixelsToUnit":100,"pivot":{"x":0.5,"y":0.5},"meshType":0}],[0],0,[0],[0],[0]],[[{"name":"100802","rect":{"x":488,"y":604,"width":290,"height":198},"offset":{"x":0,"y":0},"originalSize":{"width":302,"height":198},"rotated":true,"capInsets":[0,0,0,0],"packable":true,"pixelsToUnit":100,"pivot":{"x":0.5,"y":0.5},"meshType":0}],[0],0,[0],[0],[0]],[[{"name":"110502","rect":{"x":198,"y":3,"width":94,"height":300},"offset":{"x":0,"y":0},"originalSize":{"width":94,"height":302},"rotated":false,"capInsets":[0,0,0,0],"packable":true,"pixelsToUnit":100,"pivot":{"x":0.5,"y":0.5},"meshType":0}],[0],0,[0],[0],[0]],[[{"name":"100103","rect":{"x":114,"y":311,"width":82,"height":302},"offset":{"x":0,"y":0},"originalSize":{"width":94,"height":302},"rotated":false,"capInsets":[0,0,0,0],"packable":true,"pixelsToUnit":100,"pivot":{"x":0.5,"y":0.5},"meshType":0}],[0],0,[0],[0],[0]],[[{"name":"100703","rect":{"x":692,"y":804,"width":184,"height":198},"offset":{"x":0,"y":0},"originalSize":{"width":198,"height":198},"rotated":false,"capInsets":[0,0,0,0],"packable":true,"pixelsToUnit":100,"pivot":{"x":0.5,"y":0.5},"meshType":0}],[0],0,[0],[0],[0]],[[{"name":"100606","rect":{"x":906,"y":208,"width":100,"height":280},"offset":{"x":0,"y":-6},"originalSize":{"width":100,"height":320},"rotated":false,"capInsets":[0,0,0,0],"packable":true,"pixelsToUnit":100,"pivot":{"x":0.5,"y":0.5},"meshType":0}],[0],0,[0],[0],[0]],[[{"name":"110504","rect":{"x":3,"y":322,"width":105,"height":302},"offset":{"x":0,"y":0},"originalSize":{"width":105,"height":302},"rotated":false,"capInsets":[0,0,0,0],"packable":true,"pixelsToUnit":100,"pivot":{"x":0.5,"y":0.5},"meshType":0}],[0],0,[0],[0],[0]],[[{"name":"101204","rect":{"x":597,"y":900,"width":89,"height":92},"offset":{"x":-0.5,"y":-1},"originalSize":{"width":100,"height":100},"rotated":false,"capInsets":[0,0,0,0],"packable":true,"pixelsToUnit":100,"pivot":{"x":0.5,"y":0.5},"meshType":0}],[0],0,[0],[0],[0]],[[{"name":"110303","rect":{"x":302,"y":307,"width":94,"height":295},"offset":{"x":0,"y":-0.5},"originalSize":{"width":94,"height":302},"rotated":false,"capInsets":[0,0,0,0],"packable":true,"pixelsToUnit":100,"pivot":{"x":0.5,"y":0.5},"meshType":0}],[0],0,[0],[0],[0]],[[{"name":"100203","rect":{"x":706,"y":398,"width":191,"height":198},"offset":{"x":0.5,"y":0},"originalSize":{"width":198,"height":198},"rotated":false,"capInsets":[0,0,0,0],"packable":true,"pixelsToUnit":100,"pivot":{"x":0.5,"y":0.5},"meshType":0}],[0],0,[0],[0],[0]],[[{"name":"100204","rect":{"x":692,"y":602,"width":196,"height":198},"offset":{"x":0,"y":0},"originalSize":{"width":198,"height":198},"rotated":true,"capInsets":[0,0,0,0],"packable":true,"pixelsToUnit":100,"pivot":{"x":0.5,"y":0.5},"meshType":0}],[0],0,[0],[0],[0]],[[{"name":"110203","rect":{"x":903,"y":494,"width":198,"height":97},"offset":{"x":0,"y":0.5},"originalSize":{"width":198,"height":98},"rotated":true,"capInsets":[0,0,0,0],"packable":true,"pixelsToUnit":100,"pivot":{"x":0.5,"y":0.5},"meshType":0}],[0],0,[0],[0],[0]],[[{"name":"110503","rect":{"x":188,"y":619,"width":94,"height":300},"offset":{"x":0,"y":0},"originalSize":{"width":94,"height":302},"rotated":false,"capInsets":[0,0,0,0],"packable":true,"pixelsToUnit":100,"pivot":{"x":0.5,"y":0.5},"meshType":0}],[0],0,[0],[0],[0]],[[{"name":"100604","rect":{"x":3,"y":3,"width":94,"height":313},"offset":{"x":0,"y":0},"originalSize":{"width":94,"height":313},"rotated":false,"capInsets":[0,0,0,0],"packable":true,"pixelsToUnit":100,"pivot":{"x":0.5,"y":0.5},"meshType":0}],[0],0,[0],[0],[0]],[[{"name":"100804","rect":{"x":502,"y":299,"width":290,"height":198},"offset":{"x":0,"y":0},"originalSize":{"width":302,"height":198},"rotated":true,"capInsets":[0,0,0,0],"packable":true,"pixelsToUnit":100,"pivot":{"x":0.5,"y":0.5},"meshType":0}],[0],0,[0],[0],[0]],[[{"name":"110201","rect":{"x":882,"y":804,"width":198,"height":88},"offset":{"x":0,"y":1},"originalSize":{"width":198,"height":94},"rotated":true,"capInsets":[0,0,0,0],"packable":true,"pixelsToUnit":100,"pivot":{"x":0.5,"y":0.5},"meshType":0}],[0],0,[0],[0],[0]],[[{"name":"100104","rect":{"x":398,"y":3,"width":94,"height":295},"offset":{"x":0,"y":-0.5},"originalSize":{"width":94,"height":302},"rotated":false,"capInsets":[0,0,0,0],"packable":true,"pixelsToUnit":100,"pivot":{"x":0.5,"y":0.5},"meshType":0}],[0],0,[0],[0],[0]],[[{"name":"110304","rect":{"x":388,"y":608,"width":94,"height":295},"offset":{"x":0,"y":-0.5},"originalSize":{"width":94,"height":302},"rotated":false,"capInsets":[0,0,0,0],"packable":true,"pixelsToUnit":100,"pivot":{"x":0.5,"y":0.5},"meshType":0}],[0],0,[0],[0],[0]],[[{"name":"110301","rect":{"x":3,"y":630,"width":89,"height":302},"offset":{"x":0.5,"y":0},"originalSize":{"width":94,"height":302},"rotated":false,"capInsets":[0,0,0,0],"packable":true,"pixelsToUnit":100,"pivot":{"x":0.5,"y":0.5},"meshType":0}],[0],0,[0],[0],[0]],[[{"name":"110501","rect":{"x":402,"y":304,"width":94,"height":294},"offset":{"x":0,"y":3},"originalSize":{"width":94,"height":302},"rotated":false,"capInsets":[0,0,0,0],"packable":true,"pixelsToUnit":100,"pivot":{"x":0.5,"y":0.5},"meshType":0}],[0],0,[0],[0],[0]],[[{"name":"100602","rect":{"x":298,"y":3,"width":94,"height":298},"offset":{"x":0,"y":0},"originalSize":{"width":94,"height":302},"rotated":false,"capInsets":[0,0,0,0],"packable":true,"pixelsToUnit":100,"pivot":{"x":0.5,"y":0.5},"meshType":0}],[0],0,[0],[0],[0]],[[{"name":"110204","rect":{"x":906,"y":3,"width":199,"height":108},"offset":{"x":0,"y":0},"originalSize":{"width":199,"height":108},"rotated":true,"capInsets":[0,0,0,0],"packable":true,"pixelsToUnit":100,"pivot":{"x":0.5,"y":0.5},"meshType":0}],[0],0,[0],[0],[0]],[[{"name":"100603","rect":{"x":202,"y":309,"width":94,"height":299},"offset":{"x":0,"y":-0.5},"originalSize":{"width":94,"height":302},"rotated":false,"capInsets":[0,0,0,0],"packable":true,"pixelsToUnit":100,"pivot":{"x":0.5,"y":0.5},"meshType":0}],[0],0,[0],[0],[0]]]]
