[1,["160a29b24@6c48a"],["_textureSource"],["cc.SpriteFrame"],0,[[[{"name":"blueprint_11_10","rect":{"x":659,"y":288,"width":138,"height":143},"offset":{"x":1,"y":1.5},"originalSize":{"width":156,"height":156},"rotated":true,"capInsets":[0,0,0,0],"packable":true,"pixelsToUnit":100,"pivot":{"x":0.5,"y":0.5},"meshType":0}],[0],0,[0],[0],[0]],[[{"name":"ticketbox_icon","rect":{"x":844,"y":773,"width":80,"height":85},"offset":{"x":0,"y":0},"originalSize":{"width":80,"height":85},"rotated":false,"capInsets":[0,0,0,0],"packable":true,"pixelsToUnit":100,"pivot":{"x":0.5,"y":0.5},"meshType":0}],[0],0,[0],[0],[0]],[[{"name":"energy_icon","rect":{"x":277,"y":327,"width":79,"height":107},"offset":{"x":1,"y":0.5},"originalSize":{"width":81,"height":110},"rotated":true,"capInsets":[0,0,0,0],"packable":true,"pixelsToUnit":100,"pivot":{"x":0.5,"y":0.5},"meshType":0}],[0],0,[0],[0],[0]],[[{"name":"gem_red_box_5","rect":{"x":851,"y":155,"width":128,"height":120},"offset":{"x":0,"y":0},"originalSize":{"width":128,"height":120},"rotated":false,"capInsets":[0,0,0,0],"packable":true,"pixelsToUnit":100,"pivot":{"x":0.5,"y":0.5},"meshType":0}],[0],0,[0],[0],[0]],[[{"name":"blueprint_11_10_10","rect":{"x":179,"y":3,"width":156,"height":162},"offset":{"x":0,"y":0},"originalSize":{"width":156,"height":162},"rotated":true,"capInsets":[0,0,0,0],"packable":true,"pixelsToUnit":100,"pivot":{"x":0.5,"y":0.5},"meshType":0}],[0],0,[0],[0],[0]],[[{"name":"blueprint_10_11","rect":{"x":3,"y":146,"width":156,"height":162},"offset":{"x":0,"y":0},"originalSize":{"width":156,"height":162},"rotated":true,"capInsets":[0,0,0,0],"packable":true,"pixelsToUnit":100,"pivot":{"x":0.5,"y":0.5},"meshType":0}],[0],0,[0],[0],[0]],[[{"name":"blueprint_01_11","rect":{"x":347,"y":3,"width":156,"height":162},"offset":{"x":0,"y":0},"originalSize":{"width":156,"height":162},"rotated":true,"capInsets":[0,0,0,0],"packable":true,"pixelsToUnit":100,"pivot":{"x":0.5,"y":0.5},"meshType":0}],[0],0,[0],[0],[0]],[[{"name":"blueprint_1_1_1","rect":{"x":507,"y":294,"width":138,"height":143},"offset":{"x":1,"y":1.5},"originalSize":{"width":156,"height":156},"rotated":true,"capInsets":[0,0,0,0],"packable":true,"pixelsToUnit":100,"pivot":{"x":0.5,"y":0.5},"meshType":0}],[0],0,[0],[0],[0]],[[{"name":"equip_blue_box_8","rect":{"x":807,"y":864,"width":128,"height":119},"offset":{"x":0,"y":0},"originalSize":{"width":128,"height":119},"rotated":false,"capInsets":[0,0,0,0],"packable":true,"pixelsToUnit":100,"pivot":{"x":0.5,"y":0.5},"meshType":0}],[0],0,[0],[0],[0]],[[{"name":"blueprint_111_010","rect":{"x":808,"y":429,"width":138,"height":143},"offset":{"x":1,"y":1.5},"originalSize":{"width":156,"height":156},"rotated":true,"capInsets":[0,0,0,0],"packable":true,"pixelsToUnit":100,"pivot":{"x":0.5,"y":0.5},"meshType":0}],[0],0,[0],[0],[0]],[[{"name":"gem_red_box_6","rect":{"x":3,"y":866,"width":128,"height":120},"offset":{"x":0,"y":0},"originalSize":{"width":128,"height":120},"rotated":false,"capInsets":[0,0,0,0],"packable":true,"pixelsToUnit":100,"pivot":{"x":0.5,"y":0.5},"meshType":0}],[0],0,[0],[0],[0]],[[{"name":"blueprint_010_111","rect":{"x":515,"y":3,"width":156,"height":162},"offset":{"x":0,"y":0},"originalSize":{"width":156,"height":162},"rotated":true,"capInsets":[0,0,0,0],"packable":true,"pixelsToUnit":100,"pivot":{"x":0.5,"y":0.5},"meshType":0}],[0],0,[0],[0],[0]],[[{"name":"gold_icon","rect":{"x":121,"y":470,"width":100,"height":108},"offset":{"x":0,"y":0},"originalSize":{"width":100,"height":108},"rotated":true,"capInsets":[0,0,0,0],"packable":true,"pixelsToUnit":100,"pivot":{"x":0.5,"y":0.5},"meshType":0}],[0],0,[0],[0],[0]],[[{"name":"equip_blue_box_1","rect":{"x":3,"y":576,"width":128,"height":119},"offset":{"x":0,"y":0},"originalSize":{"width":128,"height":119},"rotated":true,"capInsets":[0,0,0,0],"packable":true,"pixelsToUnit":100,"pivot":{"x":0.5,"y":0.5},"meshType":0}],[0],0,[0],[0],[0]],[[{"name":"diamond_icon","rect":{"x":3,"y":470,"width":100,"height":112},"offset":{"x":0,"y":0},"originalSize":{"width":100,"height":112},"rotated":true,"capInsets":[0,0,0,0],"packable":true,"pixelsToUnit":100,"pivot":{"x":0.5,"y":0.5},"meshType":0}],[0],0,[0],[0],[0]],[[{"name":"gem_red_box_2","rect":{"x":137,"y":866,"width":128,"height":120},"offset":{"x":0,"y":0},"originalSize":{"width":128,"height":120},"rotated":false,"capInsets":[0,0,0,0],"packable":true,"pixelsToUnit":100,"pivot":{"x":0.5,"y":0.5},"meshType":0}],[0],0,[0],[0],[0]],[[{"name":"gem_red_box_4","rect":{"x":271,"y":866,"width":128,"height":120},"offset":{"x":0,"y":0},"originalSize":{"width":128,"height":120},"rotated":false,"capInsets":[0,0,0,0],"packable":true,"pixelsToUnit":100,"pivot":{"x":0.5,"y":0.5},"meshType":0}],[0],0,[0],[0],[0]],[[{"name":"blueprint_01_01_11","rect":{"x":656,"y":432,"width":138,"height":143},"offset":{"x":1,"y":1.5},"originalSize":{"width":156,"height":156},"rotated":true,"capInsets":[0,0,0,0],"packable":true,"pixelsToUnit":100,"pivot":{"x":0.5,"y":0.5},"meshType":0}],[0],0,[0],[0],[0]],[[{"name":"blueprint_11_01","rect":{"x":683,"y":3,"width":156,"height":162},"offset":{"x":0,"y":0},"originalSize":{"width":156,"height":162},"rotated":true,"capInsets":[0,0,0,0],"packable":true,"pixelsToUnit":100,"pivot":{"x":0.5,"y":0.5},"meshType":0}],[0],0,[0],[0],[0]],[[{"name":"equip_blue_box_6","rect":{"x":128,"y":576,"width":128,"height":119},"offset":{"x":0,"y":0},"originalSize":{"width":128,"height":119},"rotated":true,"capInsets":[0,0,0,0],"packable":true,"pixelsToUnit":100,"pivot":{"x":0.5,"y":0.5},"meshType":0}],[0],0,[0],[0],[0]],[[{"name":"equip_blue_box_2","rect":{"x":235,"y":438,"width":128,"height":119},"offset":{"x":0,"y":0},"originalSize":{"width":128,"height":119},"rotated":true,"capInsets":[0,0,0,0],"packable":true,"pixelsToUnit":100,"pivot":{"x":0.5,"y":0.5},"meshType":0}],[0],0,[0],[0],[0]],[[{"name":"equip_blue_box_7","rect":{"x":253,"y":576,"width":128,"height":119},"offset":{"x":0,"y":0},"originalSize":{"width":128,"height":119},"rotated":true,"capInsets":[0,0,0,0],"packable":true,"pixelsToUnit":100,"pivot":{"x":0.5,"y":0.5},"meshType":0}],[0],0,[0],[0],[0]],[[{"name":"equip_blue_box_5","rect":{"x":360,"y":438,"width":128,"height":119},"offset":{"x":0,"y":0},"originalSize":{"width":128,"height":119},"rotated":true,"capInsets":[0,0,0,0],"packable":true,"pixelsToUnit":100,"pivot":{"x":0.5,"y":0.5},"meshType":0}],[0],0,[0],[0],[0]],[[{"name":"food_icon","rect":{"x":507,"y":165,"width":146,"height":123},"offset":{"x":0,"y":0},"originalSize":{"width":146,"height":123},"rotated":false,"capInsets":[0,0,0,0],"packable":true,"pixelsToUnit":100,"pivot":{"x":0.5,"y":0.5},"meshType":0}],[0],0,[0],[0],[0]],[[{"name":"blueprint_11","rect":{"x":171,"y":165,"width":156,"height":162},"offset":{"x":0,"y":0},"originalSize":{"width":156,"height":162},"rotated":true,"capInsets":[0,0,0,0],"packable":true,"pixelsToUnit":100,"pivot":{"x":0.5,"y":0.5},"meshType":0}],[0],0,[0],[0],[0]],[[{"name":"equip_blue_box_9","rect":{"x":378,"y":576,"width":128,"height":119},"offset":{"x":0,"y":0},"originalSize":{"width":128,"height":119},"rotated":true,"capInsets":[0,0,0,0],"packable":true,"pixelsToUnit":100,"pivot":{"x":0.5,"y":0.5},"meshType":0}],[0],0,[0],[0],[0]],[[{"name":"equip_blue_box_4","rect":{"x":485,"y":438,"width":128,"height":119},"offset":{"x":0,"y":0},"originalSize":{"width":128,"height":119},"rotated":true,"capInsets":[0,0,0,0],"packable":true,"pixelsToUnit":100,"pivot":{"x":0.5,"y":0.5},"meshType":0}],[0],0,[0],[0],[0]],[[{"name":"blueprint_1_1","rect":{"x":805,"y":573,"width":138,"height":143},"offset":{"x":1,"y":1.5},"originalSize":{"width":156,"height":156},"rotated":true,"capInsets":[0,0,0,0],"packable":true,"pixelsToUnit":100,"pivot":{"x":0.5,"y":0.5},"meshType":0}],[0],0,[0],[0],[0]],[[{"name":"fragmentcard_3","rect":{"x":941,"y":717,"width":50,"height":43},"offset":{"x":0,"y":0},"originalSize":{"width":50,"height":43},"rotated":true,"capInsets":[0,0,0,0],"packable":true,"pixelsToUnit":100,"pivot":{"x":0.5,"y":0.5},"meshType":0}],[0],0,[0],[0],[0]],[[{"name":"gem_red_box_7","rect":{"x":405,"y":866,"width":128,"height":120},"offset":{"x":0,"y":0},"originalSize":{"width":128,"height":120},"rotated":false,"capInsets":[0,0,0,0],"packable":true,"pixelsToUnit":100,"pivot":{"x":0.5,"y":0.5},"meshType":0}],[0],0,[0],[0],[0]],[[{"name":"equip_blue_box_10","rect":{"x":503,"y":576,"width":128,"height":119},"offset":{"x":0,"y":0},"originalSize":{"width":128,"height":119},"rotated":true,"capInsets":[0,0,0,0],"packable":true,"pixelsToUnit":100,"pivot":{"x":0.5,"y":0.5},"meshType":0}],[0],0,[0],[0],[0]],[[{"name":"gem_red_box_3","rect":{"x":539,"y":866,"width":128,"height":120},"offset":{"x":0,"y":0},"originalSize":{"width":128,"height":120},"rotated":false,"capInsets":[0,0,0,0],"packable":true,"pixelsToUnit":100,"pivot":{"x":0.5,"y":0.5},"meshType":0}],[0],0,[0],[0],[0]],[[{"name":"blueprint_111","rect":{"x":3,"y":308,"width":156,"height":162},"offset":{"x":0,"y":0},"originalSize":{"width":156,"height":162},"rotated":true,"capInsets":[0,0,0,0],"packable":true,"pixelsToUnit":100,"pivot":{"x":0.5,"y":0.5},"meshType":0}],[0],0,[0],[0],[0]],[[{"name":"blueprint_10_11_01","rect":{"x":3,"y":717,"width":138,"height":143},"offset":{"x":1,"y":1.5},"originalSize":{"width":156,"height":156},"rotated":false,"capInsets":[0,0,0,0],"packable":true,"pixelsToUnit":100,"pivot":{"x":0.5,"y":0.5},"meshType":0}],[0],0,[0],[0],[0]],[[{"name":"blueprint_11_11","rect":{"x":147,"y":717,"width":138,"height":143},"offset":{"x":1,"y":1.5},"originalSize":{"width":156,"height":156},"rotated":false,"capInsets":[0,0,0,0],"packable":true,"pixelsToUnit":100,"pivot":{"x":0.5,"y":0.5},"meshType":0}],[0],0,[0],[0],[0]],[[{"name":"icon_revive","rect":{"x":171,"y":327,"width":100,"height":103},"offset":{"x":0,"y":0},"originalSize":{"width":100,"height":103},"rotated":false,"capInsets":[0,0,0,0],"packable":true,"pixelsToUnit":100,"pivot":{"x":0.5,"y":0.5},"meshType":0}],[0],0,[0],[0],[0]],[[{"name":"box_key_2","rect":{"x":659,"y":165,"width":117,"height":145},"offset":{"x":0,"y":-0.5},"originalSize":{"width":159,"height":158},"rotated":true,"capInsets":[0,0,0,0],"packable":true,"pixelsToUnit":100,"pivot":{"x":0.5,"y":0.5},"meshType":0}],[0],0,[0],[0],[0]],[[{"name":"box_key_1","rect":{"x":723,"y":717,"width":115,"height":141},"offset":{"x":0,"y":-0.5},"originalSize":{"width":159,"height":158},"rotated":false,"capInsets":[0,0,0,0],"packable":true,"pixelsToUnit":100,"pivot":{"x":0.5,"y":0.5},"meshType":0}],[0],0,[0],[0],[0]],[[{"name":"fragmentcard_2","rect":{"x":844,"y":717,"width":50,"height":43},"offset":{"x":0,"y":0},"originalSize":{"width":50,"height":43},"rotated":true,"capInsets":[0,0,0,0],"packable":true,"pixelsToUnit":100,"pivot":{"x":0.5,"y":0.5},"meshType":0}],[0],0,[0],[0],[0]],[[{"name":"gem_red_box_1","rect":{"x":673,"y":866,"width":128,"height":120},"offset":{"x":0,"y":0},"originalSize":{"width":128,"height":120},"rotated":false,"capInsets":[0,0,0,0],"packable":true,"pixelsToUnit":100,"pivot":{"x":0.5,"y":0.5},"meshType":0}],[0],0,[0],[0],[0]],[[{"name":"weapon_blueprint_icon","rect":{"x":291,"y":717,"width":138,"height":143},"offset":{"x":1,"y":1.5},"originalSize":{"width":156,"height":156},"rotated":false,"capInsets":[0,0,0,0],"packable":true,"pixelsToUnit":100,"pivot":{"x":0.5,"y":0.5},"meshType":0}],[0],0,[0],[0],[0]],[[{"name":"blueprint_1111","rect":{"x":339,"y":165,"width":156,"height":162},"offset":{"x":0,"y":0},"originalSize":{"width":156,"height":162},"rotated":true,"capInsets":[0,0,0,0],"packable":true,"pixelsToUnit":100,"pivot":{"x":0.5,"y":0.5},"meshType":0}],[0],0,[0],[0],[0]],[[{"name":"blueprint_1","rect":{"x":435,"y":717,"width":138,"height":143},"offset":{"x":1,"y":1.5},"originalSize":{"width":156,"height":156},"rotated":false,"capInsets":[0,0,0,0],"packable":true,"pixelsToUnit":100,"pivot":{"x":0.5,"y":0.5},"meshType":0}],[0],0,[0],[0],[0]],[[{"name":"equip_blueprint_icon","rect":{"x":810,"y":281,"width":142,"height":144},"offset":{"x":0,"y":0},"originalSize":{"width":142,"height":144},"rotated":true,"capInsets":[0,0,0,0],"packable":true,"pixelsToUnit":100,"pivot":{"x":0.5,"y":0.5},"meshType":0}],[0],0,[0],[0],[0]],[[{"name":"blueprint_1_1_1_1","rect":{"x":579,"y":717,"width":138,"height":143},"offset":{"x":1,"y":1.5},"originalSize":{"width":156,"height":156},"rotated":false,"capInsets":[0,0,0,0],"packable":true,"pixelsToUnit":100,"pivot":{"x":0.5,"y":0.5},"meshType":0}],[0],0,[0],[0],[0]],[[{"name":"exp_icon","rect":{"x":851,"y":3,"width":146,"height":134},"offset":{"x":-1,"y":-2},"originalSize":{"width":156,"height":156},"rotated":true,"capInsets":[0,0,0,0],"packable":true,"pixelsToUnit":100,"pivot":{"x":0.5,"y":0.5},"meshType":0}],[0],0,[0],[0],[0]],[[{"name":"equip_blue_box_3","rect":{"x":628,"y":576,"width":128,"height":119},"offset":{"x":0,"y":0},"originalSize":{"width":128,"height":119},"rotated":true,"capInsets":[0,0,0,0],"packable":true,"pixelsToUnit":100,"pivot":{"x":0.5,"y":0.5},"meshType":0}],[0],0,[0],[0],[0]],[[{"name":"ticket_icon","rect":{"x":3,"y":3,"width":170,"height":137},"offset":{"x":0,"y":0},"originalSize":{"width":170,"height":137},"rotated":false,"capInsets":[0,0,0,0],"packable":true,"pixelsToUnit":100,"pivot":{"x":0.5,"y":0.5},"meshType":0}],[0],0,[0],[0],[0]],[[{"name":"fragmentcard_1","rect":{"x":941,"y":773,"width":50,"height":43},"offset":{"x":0,"y":0},"originalSize":{"width":50,"height":43},"rotated":true,"capInsets":[0,0,0,0],"packable":true,"pixelsToUnit":100,"pivot":{"x":0.5,"y":0.5},"meshType":0}],[0],0,[0],[0],[0]]]]
